SimpleCalculator.py
pySimpleCalculator-0.0.1.dist-info/LICENSE
pySimpleCalculator-0.0.1.dist-info/METADATA
pySimpleCalculator-0.0.1.dist-info/WHEEL
pySimpleCalculator-0.0.1.dist-info/top_level.txt
pySimpleCalculator-0.0.1.dist-info/RECORD
