Metadata-Version: 2.1
Name: pySimpleCalculator
Version: 0.0.1
Summary: A simple calculator for arithmetic operations in python
Home-page: https://github.com/Sherlocked-Blaire/PySimpleCalculator.git
Author: Blessing .O. Agadagba
Author-email: agadagbablessing@gmail.com
License: UNKNOWN
Project-URL: Bug Tracker, https://github.com/Sherlocked-Blaire/PySimpleCalculator/issues
Platform: UNKNOWN
Classifier: Programming Language :: Python :: 3
Classifier: License :: OSI Approved :: MIT License
Classifier: Operating System :: OS Independent
Requires-Python: >=3.6
License-File: LICENSE
